llments/__init__.py
llments/version.py
llments/distance/distance.py
llments/distance/norm.py
llments/eval/__init__.py
llments/eval/eval.py
llments/lm/__init__.py
llments/lm/empirical.py
llments/lm/hugging_face.py
llments/lm/lm.py
llments/lm/lm_loader.py
llments/lm/lm_loader_test.py
llments-0.0.0a2.dist-info/METADATA
llments-0.0.0a2.dist-info/WHEEL
llments-0.0.0a2.dist-info/licenses/LICENSE.txt
llments-0.0.0a2.dist-info/RECORD
